jrnmm/__init__.py
jrnmm/simulator.py
jrnmm/simulator_test.py
jrnmm-0.1.1.post2.dist-info/LICENSE
jrnmm-0.1.1.post2.dist-info/METADATA
jrnmm-0.1.1.post2.dist-info/WHEEL
jrnmm-0.1.1.post2.dist-info/top_level.txt
jrnmm-0.1.1.post2.dist-info/RECORD
