Metadata-Version: 2.2
Name: jrnmm
Version: 0.1.1.post2
Summary: Simulating trajectories from the stochastic Jansen-Rit neural mass model
Author-email: Simon Dirmeier <sfyrbnd@pm.me>
License: 
Project-URL: Homepage, https://github.com/dirmeier/jrnmm
Classifier: Development Status :: 1 - Planning
Classifier: Intended Audience :: Science/Research
Classifier: Programming Language :: Python :: 3
Classifier: Programming Language :: Python :: 3.9
Classifier: Programming Language :: Python :: 3.11
Classifier: Programming Language :: Python :: 3.12
Requires-Python: >=3.9
License-File: LICENSE
Requires-Dist: jax>=0.4.17
Requires-Dist: numpy>=1.24.4
Requires-Dist: chex>=0.1.85
Requires-Dist: einops>=0.8.0
